bibcites/.DS_Store
bibcites/__init__.py
bibcites-2.0.1.dist-info/WHEEL
bibcites-2.0.1.dist-info/entry_points.txt
bibcites-2.0.1.dist-info/METADATA
bibcites-2.0.1.dist-info/RECORD
