Metadata-Version: 2.3
Name: bibcites
Version: 2.0.1
Author: Mathieu Daëron
Author-email: Mathieu Daëron <mathieu@daeron.fr>
Classifier: Programming Language :: Python :: 3
Classifier: License :: OSI Approved :: MIT License
Classifier: Operating System :: OS Independent
Requires-Dist: opencitingpy>=0.1
Requires-Dist: bibtexparser>=1.2
Requires-Dist: click>=8.0
Requires-Dist: tqdm==4.67.*
Requires-Python: >=3.11
Project-URL: Home, https://github.com/mdaeron/bibcites
